cryptolibs/__init__.py
cryptolibs-1.2.0.dist-info/METADATA
cryptolibs-1.2.0.dist-info/WHEEL
cryptolibs-1.2.0.dist-info/top_level.txt
cryptolibs-1.2.0.dist-info/RECORD
