Metadata-Version: 2.1
Name: cryptolibs
Version: 1.2.0
Summary: Package that helps with crypto libarys
Home-page: UNKNOWN
Author: NHJonas
Author-email: nick.faltermeier@gmx.de
License: UNKNOWN
Keywords: python
Platform: UNKNOWN
Classifier: Operating System :: Microsoft :: Windows
